{"cameraMode":{"drawMode":0,"name":"Shaded","section":"Shading Mode"},"sceneLighting":true,"audioPlay":false,"sceneViewState":{"m_AlwaysRefresh":false,"showFog":true,"showSkybox":true,"showFlares":true,"showImageEffects":true,"showParticleSystems":true,"showVisualEffectGraphs":true,"m_FxEnabled":true},"in2DMode":false,"pivot":{"x":545.7548217773438,"y":-25.79549789428711,"z":544.3723754882813},"rotation":{"x":0.5110684037208557,"y":-0.0018112711841240526,"z":0.001040780101902783,"w":0.8595736026763916},"size":53.200191497802737,"orthographic":false}